aiowithings/__init__.py
aiowithings/const.py
aiowithings/exceptions.py
aiowithings/helpers.py
aiowithings/models.py
aiowithings/py.typed
aiowithings/util.py
aiowithings/withings.py
aiowithings-3.1.5.dist-info/LICENSE.md
aiowithings-3.1.5.dist-info/METADATA
aiowithings-3.1.5.dist-info/WHEEL
aiowithings-3.1.5.dist-info/RECORD
